ai_data_science_team/__init__.py
ai_data_science_team/_version.py
ai_data_science_team/orchestration.py
ai_data_science_team/agents/__init__.py
ai_data_science_team/agents/data_cleaning_agent.py
ai_data_science_team/agents/data_wrangling_agent.py
ai_data_science_team/agents/feature_engineering_agent.py
ai_data_science_team/agents/sql_database_agent.py
ai_data_science_team/templates/__init__.py
ai_data_science_team/templates/agent_templates.py
ai_data_science_team/tools/__init__.py
ai_data_science_team/tools/logging.py
ai_data_science_team/tools/metadata.py
ai_data_science_team/tools/parsers.py
ai_data_science_team/tools/regex.py
ai_data_science_team-0.0.0.90061.dist-info/LICENSE
ai_data_science_team-0.0.0.90061.dist-info/METADATA
ai_data_science_team-0.0.0.90061.dist-info/WHEEL
ai_data_science_team-0.0.0.90061.dist-info/top_level.txt
ai_data_science_team-0.0.0.90061.dist-info/RECORD
