Metadata-Version: 2.1
Name: ai-data-science-team
Version: 0.0.0.90061
Summary: Build and run an AI-powered data science team.
Home-page: https://github.com/business-science/ai-data-science-team
Author: Matt Dancho
Author-email: mdancho@business-science.io
Requires-Python: >=3.9
License-File: LICENSE
Requires-Dist: openpyxl
Requires-Dist: langchain
Requires-Dist: langchain_community
Requires-Dist: langchain_openai
Requires-Dist: langchain_experimental
Requires-Dist: langgraph>=0.2.57
Requires-Dist: openai
Requires-Dist: pandas
Requires-Dist: numpy
Requires-Dist: plotly
Requires-Dist: streamlit
Requires-Dist: scikit-learn
Requires-Dist: xgboost
